setup.py
rolld/__init__.py
rolld/manager.py
rolld.egg-info/PKG-INFO
rolld.egg-info/SOURCES.txt
rolld.egg-info/dependency_links.txt
rolld.egg-info/entry_points.txt
rolld.egg-info/requires.txt
rolld.egg-info/top_level.txt