Metadata-Version: 1.1
Name: rolld
Version: 0.1.1
Summary: hassle free process restarting
Home-page: https://github.com/ybrs/project-switcher
Author: ybrs
Author-email: aybars.badur@gmail.com
License: MIT
Platform: UNKNOWN
Classifier: Development Status :: 4 - Beta
Classifier: Intended Audience :: Developers
Classifier: License :: OSI Approved :: MIT License
Classifier: Operating System :: OS Independent
Classifier: Programming Language :: Python
Classifier: Topic :: Database
Classifier: Topic :: Software Development :: Libraries :: Python Modules
